qconfig/__init__.py
qconfig/_hook.py
qconfig/_method_loader.py
qconfig/_xml_tools.py
qconfig/dynamic_loader.py
qconfig/exceptions.py
qconfig/py.typed
qconfig/qconfig.py
qconfig/tools.py
qtconfig-0.0.5.dist-info/LICENSE
qtconfig-0.0.5.dist-info/METADATA
qtconfig-0.0.5.dist-info/WHEEL
qtconfig-0.0.5.dist-info/top_level.txt
qtconfig-0.0.5.dist-info/RECORD
