Metadata-Version: 2.1
Name: qtconfig
Version: 0.0.5
Summary: A helper package to store and load PyQt GUI configurations
Author-email: Kenny Hommel <kennyhommel36@gmail.com>
Project-URL: Homepage, https://github.com/kennyhml/QConfig
Project-URL: Bug Tracker, https://github.com/kennyhml/QConfig/issues
Classifier: Programming Language :: Python :: 3
Classifier: License :: OSI Approved :: MIT License
Classifier: Operating System :: OS Independent
Requires-Python: >=3.10
License-File: LICENSE
Requires-Dist: pyside6
Requires-Dist: PyYAML
